setup.py
VidInteract/ToVid.py
VidInteract/__init__.py
pyvidnteract.egg-info/PKG-INFO
pyvidnteract.egg-info/SOURCES.txt
pyvidnteract.egg-info/dependency_links.txt
pyvidnteract.egg-info/requires.txt
pyvidnteract.egg-info/top_level.txt