Metadata-Version: 1.0
Name: pyvidnteract
Version: 0.1.0
Summary: A way to interact with video files in python.
Home-page: UNKNOWN
Author: UNKNOWN
Author-email: UNKNOWN
License: UNKNOWN
Platform: UNKNOWN
